duragraph/__init__.py
duragraph/edges.py
duragraph/graph.py
duragraph/nodes.py
duragraph/py.typed
duragraph/types.py
duragraph/cli/__init__.py
duragraph/cli/main.py
duragraph/prompts/__init__.py
duragraph/prompts/decorators.py
duragraph/prompts/store.py
duragraph/worker/__init__.py
duragraph/worker/worker.py
duragraph_python-0.1.0.dist-info/METADATA
duragraph_python-0.1.0.dist-info/WHEEL
duragraph_python-0.1.0.dist-info/entry_points.txt
duragraph_python-0.1.0.dist-info/licenses/LICENSE
duragraph_python-0.1.0.dist-info/RECORD
