Metadata-Version: 2.4
Name: duragraph-python
Version: 0.1.0
Summary: Python SDK for DuraGraph - Reliable AI Workflow Orchestration
Project-URL: Homepage, https://duragraph.io
Project-URL: Documentation, https://docs.duragraph.io
Project-URL: Repository, https://github.com/duragraph/duragraph-python
Project-URL: Issues, https://github.com/duragraph/duragraph-python/issues
Project-URL: Changelog, https://github.com/duragraph/duragraph-python/blob/main/CHANGELOG.md
Author-email: DuraGraph Team <team@duragraph.io>
License-Expression: Apache-2.0
License-File: LICENSE
Keywords: agents,ai,langgraph,llm,orchestration,workflows
Classifier: Development Status :: 3 - Alpha
Classifier: Intended Audience :: Developers
Classifier: License :: OSI Approved :: Apache Software License
Classifier: Programming Language :: Python :: 3
Classifier: Programming Language :: Python :: 3.10
Classifier: Programming Language :: Python :: 3.11
Classifier: Programming Language :: Python :: 3.12
Classifier: Programming Language :: Python :: 3.13
Classifier: Topic :: Scientific/Engineering :: Artificial Intelligence
Classifier: Typing :: Typed
Requires-Python: >=3.10
Requires-Dist: httpx>=0.27.0
Requires-Dist: pydantic>=2.0.0
Requires-Dist: typing-extensions>=4.0.0
Provides-Extra: all
Requires-Dist: anthropic>=0.30.0; extra == 'all'
Requires-Dist: openai>=1.0.0; extra == 'all'
Requires-Dist: opentelemetry-api>=1.20.0; extra == 'all'
Requires-Dist: opentelemetry-sdk>=1.20.0; extra == 'all'
Provides-Extra: anthropic
Requires-Dist: anthropic>=0.30.0; extra == 'anthropic'
Provides-Extra: dev
Requires-Dist: mypy>=1.10.0; extra == 'dev'
Requires-Dist: pre-commit>=3.0.0; extra == 'dev'
Requires-Dist: pytest-asyncio>=0.23.0; extra == 'dev'
Requires-Dist: pytest-cov>=4.0.0; extra == 'dev'
Requires-Dist: pytest>=8.0.0; extra == 'dev'
Requires-Dist: ruff>=0.4.0; extra == 'dev'
Provides-Extra: docs
Requires-Dist: mkdocs-material>=9.0.0; extra == 'docs'
Requires-Dist: mkdocs>=1.5.0; extra == 'docs'
Requires-Dist: mkdocstrings[python]>=0.24.0; extra == 'docs'
Provides-Extra: openai
Requires-Dist: openai>=1.0.0; extra == 'openai'
